strayl_mcp_server/__init__.py
strayl_mcp_server/__main__.py
strayl_mcp_server/server.py
strayl_mcp_server/utils.py
strayl_mcp_server-0.1.3.dist-info/METADATA
strayl_mcp_server-0.1.3.dist-info/WHEEL
strayl_mcp_server-0.1.3.dist-info/entry_points.txt
strayl_mcp_server-0.1.3.dist-info/licenses/LICENSE
strayl_mcp_server-0.1.3.dist-info/RECORD
