Metadata-Version: 2.4
Name: strayl-mcp-server
Version: 0.1.3
Summary: MCP server for Strayl log search with semantic and exact search capabilities
Project-URL: Homepage, https://strayl.dev
Project-URL: Documentation, https://docs.strayl.dev
Project-URL: Repository, https://github.com/strayl/strayl-mcp-server
Project-URL: Issues, https://github.com/strayl/strayl-mcp-server/issues
Author-email: Strayl <support@strayl.dev>
License: MIT
License-File: LICENSE
Keywords: ai,logging,mcp,search,strayl
Classifier: Development Status :: 3 - Alpha
Classifier: Intended Audience :: Developers
Classifier: License :: OSI Approved :: MIT License
Classifier: Programming Language :: Python :: 3
Classifier: Programming Language :: Python :: 3.10
Classifier: Programming Language :: Python :: 3.11
Classifier: Programming Language :: Python :: 3.12
Requires-Python: >=3.10
Requires-Dist: httpx>=0.27.0
Requires-Dist: mcp>=0.9.0
Requires-Dist: python-dateutil>=2.8.0
Provides-Extra: dev
Requires-Dist: black>=23.0.0; extra == 'dev'
Requires-Dist: pytest-asyncio>=0.21.0; extra == 'dev'
Requires-Dist: pytest>=7.0.0; extra == 'dev'
Requires-Dist: ruff>=0.1.0; extra == 'dev'
